universal_mcp/agentr/README.md
universal_mcp/agentr/__init__.py
universal_mcp/agentr/agent_builder_registry.py
universal_mcp/agentr/client.py
universal_mcp/agentr/integration.py
universal_mcp/agentr/registry.py
universal_mcp/agentr/server.py
universal_mcp/agentr/types.py
universal_mcp/agents/__init__.py
universal_mcp/agents/base.py
universal_mcp/agents/cli.py
universal_mcp/agents/hil.py
universal_mcp/agents/llm.py
universal_mcp/agents/react.py
universal_mcp/agents/simple.py
universal_mcp/agents/utils.py
universal_mcp/agents/bigtool/__init__.py
universal_mcp/agents/bigtool/__main__.py
universal_mcp/agents/bigtool/agent.py
universal_mcp/agents/bigtool/context.py
universal_mcp/agents/bigtool/graph.py
universal_mcp/agents/bigtool/prompts.py
universal_mcp/agents/bigtool/state.py
universal_mcp/agents/bigtool/tools.py
universal_mcp/agents/builder/__main__.py
universal_mcp/agents/builder/builder.py
universal_mcp/agents/builder/helper.py
universal_mcp/agents/builder/prompts.py
universal_mcp/agents/builder/state.py
universal_mcp/agents/codeact0/__init__.py
universal_mcp/agents/codeact0/__main__.py
universal_mcp/agents/codeact0/agent.py
universal_mcp/agents/codeact0/agent_transient.py
universal_mcp/agents/codeact0/langgraph_agent.py
universal_mcp/agents/codeact0/llm_tool.py
universal_mcp/agents/codeact0/prompts.py
universal_mcp/agents/codeact0/sandbox.py
universal_mcp/agents/codeact0/state.py
universal_mcp/agents/codeact0/state_transient.py
universal_mcp/agents/codeact0/tools.py
universal_mcp/agents/codeact0/utils.py
universal_mcp/agents/codeact0/nodes/__init__.py
universal_mcp/agents/codeact0/nodes/planner.py
universal_mcp/agents/storm/__init__.py
universal_mcp/agents/storm/__main__.py
universal_mcp/agents/storm/agent.py
universal_mcp/agents/storm/langgraph_agent.py
universal_mcp/agents/storm/prompts.py
universal_mcp/agents/storm/sandbox.py
universal_mcp/agents/storm/state.py
universal_mcp/agents/storm/nodes/__init__.py
universal_mcp/agents/storm/nodes/agent_node.py
universal_mcp_agents-0.1.28.dist-info/METADATA
universal_mcp_agents-0.1.28.dist-info/WHEEL
universal_mcp_agents-0.1.28.dist-info/RECORD
