Metadata-Version: 2.4
Name: universal-mcp-agents
Version: 0.1.28
Summary: Add your description here
Project-URL: Homepage, https://github.com/universal-mcp/applications
Project-URL: Repository, https://github.com/universal-mcp/applications
Author-email: Manoj Bajaj <manojbajaj95@gmail.com>
License: MIT
Requires-Python: >=3.11
Requires-Dist: cloudpickle>=3.1.1
Requires-Dist: json-schema-to-pydantic>=0.4.7
Requires-Dist: langchain-anthropic>=0.3.19
Requires-Dist: langchain-aws>=1.1.0
Requires-Dist: langchain-google-genai>=2.1.10
Requires-Dist: langchain-openai>=0.3.32
Requires-Dist: langgraph>=0.6.6
Requires-Dist: universal-mcp-applications>=0.1.36rc3
Requires-Dist: universal-mcp>=0.1.24rc29
Provides-Extra: dev
Requires-Dist: pre-commit; extra == 'dev'
Requires-Dist: ruff; extra == 'dev'
Requires-Dist: typer>=0.17.4; extra == 'dev'
Provides-Extra: test
Requires-Dist: pytest-asyncio>=1.2.0; extra == 'test'
Requires-Dist: pytest-cov; extra == 'test'
Requires-Dist: pytest<9.0.0,>=7.0.0; extra == 'test'
